gradvar/__init__.py
gradvar/earlystopping.py
gradvar/gradvar.py
gradvar-2025.3.1.dist-info/METADATA
gradvar-2025.3.1.dist-info/WHEEL
gradvar-2025.3.1.dist-info/top_level.txt
gradvar-2025.3.1.dist-info/RECORD
