Metadata-Version: 2.4
Name: GradVAR
Version: 2025.3.1
Summary: Gradient update Vector Autoregression modeling library
Author: Martin Forsberg Lie
Author-email: Martin Forsberg Lie <martin.lie@gmail.com>
Maintainer-email: Martin Forsberg Lie <martin.lie@gmail.com>
License-Expression: MIT
Project-URL: Repository, https://github.com/martinlie/GradVAR.git
Project-URL: Issues, https://github.com/martinlie/GradVAR/issues
Project-URL: Changelog, https://github.com/martinlie/GradVAR/activity
Classifier: Development Status :: 4 - Beta
Classifier: Programming Language :: Python
Requires-Python: >=3.9
Requires-Dist: jax
Requires-Dist: optax
Requires-Dist: tqdm
Dynamic: author
